double_cartpole_custom_gym_env/Cartpole.py
double_cartpole_custom_gym_env/__init__.py
double_cartpole_custom_gym_env/double_cartpole_env.py
double_cartpole_custom_gym_env/event_handler.py
double_cartpole_custom_gym_env/img/icon.png
double_cartpole_custom_gym_env-1.1.3.dist-info/METADATA
double_cartpole_custom_gym_env-1.1.3.dist-info/WHEEL
double_cartpole_custom_gym_env-1.1.3.dist-info/top_level.txt
double_cartpole_custom_gym_env-1.1.3.dist-info/RECORD
