Metadata-Version: 2.1
Name: double-cartpole-custom-gym-env
Version: 1.1.3
Summary: OpenAI Gym environment designed for training RL agents to balance double CartPole.
Home-page: https://github.com/marek-robak/Double-cartpole-custom-gym-env-for-reinforcement-learning.git
Download-URL: https://pypi.org/project/double-cartpole-custom-gym-env/
Author: Marek Robak
Author-email: maro.robak@gmail.com
License: UNKNOWN
Keywords: reinforcement learning,gym environment,StableBaselines3,OpenAI Gym
Platform: UNKNOWN
Requires-Dist: gym
Requires-Dist: pygame
Requires-Dist: pymunk
Requires-Dist: numpy
Requires-Dist: stable-baselines3[extra]
